clamshell/__init__.py
clamshell/__main__.py
clamshell/defaults.py
clamshell/key_bindings.py
clamshell/meta_functions.py
clamshell/shell.py
clamshell/shell_utils.py
clamshell/types.py
clamshell-0.4.dist-info/entry_points.txt
clamshell-0.4.dist-info/WHEEL
clamshell-0.4.dist-info/METADATA
clamshell-0.4.dist-info/RECORD
