Metadata-Version: 2.1
Name: clamshell
Version: 0.4
Summary: An experimental shell for the modern age!
Requires-Python: >=3.6
Requires-Dist: send2trash
Requires-Dist: prompt-toolkit
Requires-Dist: pygments
Requires-Dist: rich
